{
   "author" : {
      "name" : "Nigel Horne",
      "github" : "nigelhorne",
      "cpan" : "NHORNE",
      "gravatar" : "https://www.bandsman.co.uk/images/njh_photo.jpg"
   },
   "ci" : {
      "use_travis" : 1,
      "use_cirrus" : 0,
      "use_gh_actions" : 1,
      "use_kritika" : 0,
      "use_travis_com" : 0,
      "gh_workflow_names" : [
         "CI"
      ],
      "use_codecov" : 0,
      "use_appveyor" : 1,
      "use_coveralls" : 1
   },
   "modules" : [
      {
         "repo_name" : "CGI-ACL",
         "name" : "CGI-ACL-0.04",
         "uses_rt" : "",
         "repo_def_branch" : "master",
         "date" : "2021-05-21",
         "insecure_repo" : "",
         "dist" : "CGI-ACL",
         "repo_owner" : "nigelhorne",
         "bugtracker" : "https://github.com/nigelhorne/CGI-ACL/issues",
         "repo" : "https://github.com/nigelhorne/CGI-ACL"
      },
      {
         "dist" : "CGI-Buffer",
         "bugtracker" : "https://github.com/nigelhorne/CGI-Buffer/issues",
         "repo" : "https://github.com/nigelhorne/CGI-Buffer",
         "repo_owner" : "nigelhorne",
         "uses_rt" : "",
         "name" : "CGI-Buffer-0.83",
         "repo_name" : "CGI-Buffer",
         "date" : "2023-02-24",
         "insecure_repo" : "",
         "repo_def_branch" : "master"
      },
      {
         "uses_rt" : "",
         "name" : "CGI-Info-0.75",
         "repo_name" : "CGI-Info",
         "date" : "2023-04-15",
         "insecure_repo" : "",
         "repo_def_branch" : "master",
         "dist" : "CGI-Info",
         "bugtracker" : "https://github.com/nigelhorne/CGI-Info/issues",
         "repo" : "https://github.com/nigelhorne/CGI-Info",
         "repo_owner" : "nigelhorne"
      },
      {
         "dist" : "CGI-Lingua",
         "repo_owner" : "nigelhorne",
         "repo" : "https://github.com/nigelhorne/CGI-Lingua",
         "bugtracker" : "https://github.com/nigelhorne/CGI-Lingua/issues",
         "repo_name" : "CGI-Lingua",
         "name" : "CGI-Lingua-0.64",
         "uses_rt" : "",
         "repo_def_branch" : "master",
         "date" : "2022-01-25",
         "insecure_repo" : ""
      },
      {
         "date" : "2019-12-15",
         "insecure_repo" : "",
         "repo_def_branch" : "master",
         "uses_rt" : "1",
         "name" : "CGI-Untaint-CountyStateProvince-0.06",
         "repo_name" : "CGI-Untaint-CountyStateProvince",
         "repo" : "https://github.com/nigelhorne/CGI-Untaint-CountyStateProvince",
         "bugtracker" : "https://rt.cpan.org/Public/Dist/Display.html?Name=CGI-Untaint-CountyStateProvince",
         "repo_owner" : "nigelhorne",
         "dist" : "CGI-Untaint-CountyStateProvince"
      },
      {
         "dist" : "CGI-Untaint-CountyStateProvince-GB",
         "repo_owner" : "nigelhorne",
         "repo" : "https://github.com/nigelhorne/CGI-Untaint-CountyStateProvince-GB",
         "repo_name" : "CGI-Untaint-CountyStateProvince-GB",
         "name" : "CGI-Untaint-CountyStateProvince-GB-0.12",
         "repo_def_branch" : "master",
         "insecure_repo" : "",
         "date" : "2019-12-11"
      },
      {
         "repo_name" : "CGI-Untaint-Facebook",
         "name" : "CGI-Untaint-Facebook-0.16",
         "repo_def_branch" : "master",
         "date" : "2023-04-14",
         "insecure_repo" : "",
         "dist" : "CGI-Untaint-Facebook",
         "repo_owner" : "nigelhorne",
         "repo" : "https://github.com/nigelhorne/CGI-Untaint-Facebook"
      },
      {
         "repo_owner" : "nigelhorne",
         "repo" : "https://github.com/nigelhorne/CGI-Untaint-Twitter",
         "dist" : "CGI-Untaint-Twitter",
         "repo_def_branch" : "master",
         "insecure_repo" : "",
         "date" : "2019-12-03",
         "repo_name" : "CGI-Untaint-Twitter",
         "name" : "CGI-Untaint-Twitter-0.05"
      },
      {
         "bugtracker" : "https://github.com/nigelhorne/Class-Simple-Cached/issues",
         "repo" : "https://github.com/nigelhorne/Class-Simple-Cached",
         "repo_owner" : "nigelhorne",
         "dist" : "Class-Simple-Cached",
         "insecure_repo" : "",
         "date" : "2021-03-02",
         "repo_def_branch" : "master",
         "name" : "Class-Simple-Cached-0.04",
         "uses_rt" : "",
         "repo_name" : "Class-Simple-Cached"
      },
      {
         "dist" : "Class-Simple-Readonly-Cached",
         "repo_owner" : "nigelhorne",
         "repo" : "https://github.com/nigelhorne/Class-Simple-Readonly-Cached",
         "bugtracker" : "https://github.com/nigelhorne/Class-Simple-Readonly-Cached/issues",
         "repo_name" : "Class-Simple-Readonly-Cached",
         "name" : "Class-Simple-Readonly-Cached-0.09",
         "uses_rt" : "",
         "repo_def_branch" : "master",
         "insecure_repo" : "",
         "date" : "2023-03-13"
      },
      {
         "repo" : "https://github.com/nigelhorne/Comment-Spell",
         "bugtracker" : "https://github.com/nigelhorne/Comment-Spell/issues",
         "repo_owner" : "nigelhorne",
         "dist" : "Comment-Spell",
         "date" : "2021-04-30",
         "insecure_repo" : "",
         "repo_def_branch" : "master",
         "name" : "Comment-Spell-0.001004",
         "uses_rt" : "",
         "repo_name" : "Comment-Spell"
      },
      {
         "insecure_repo" : "",
         "date" : "2017-09-03",
         "repo_def_branch" : "master",
         "name" : "DBD-XMLSimple-0.06",
         "repo_name" : "DBD-XMLSimple",
         "repo" : "https://github.com/nigelhorne/DBD-XMLSimple",
         "repo_owner" : "nigelhorne",
         "dist" : "DBD-XMLSimple"
      },
      {
         "repo_name" : "DBIx-AnyDBD",
         "uses_rt" : "",
         "name" : "DBIx-AnyDBD-2.03",
         "repo_def_branch" : "master",
         "date" : "2020-11-14",
         "insecure_repo" : "",
         "dist" : "DBIx-AnyDBD",
         "repo_owner" : "nigelhorne",
         "bugtracker" : "https://github.com/nigelhorne/DBIx-AnyDBD/issues",
         "repo" : "https://github.com/nigelhorne/DBIx-AnyDBD"
      },
      {
         "bugtracker" : "https://github.com/nigelhorne/Data-Fetch/issues",
         "repo" : "https://github.com/nigelhorne/Data-Fetch",
         "repo_owner" : "nigelhorne",
         "dist" : "Data-Fetch",
         "date" : "2020-11-24",
         "insecure_repo" : "",
         "repo_def_branch" : "master",
         "uses_rt" : "",
         "name" : "Data-Fetch-0.06",
         "repo_name" : "Data-Fetch"
      },
      {
         "dist" : "Data-Text",
         "bugtracker" : "https://github.com/nigelhorne/Data-Text/issues",
         "repo" : "https://github.com/nigelhorne/Data-Text",
         "repo_owner" : "nigelhorne",
         "name" : "Data-Text-0.11",
         "uses_rt" : "",
         "repo_name" : "Data-Text",
         "date" : "2022-12-22",
         "insecure_repo" : "",
         "repo_def_branch" : "master"
      },
      {
         "repo_name" : "DateTime-Format-Genealogy",
         "name" : "DateTime-Format-Genealogy-0.05",
         "uses_rt" : "",
         "repo_def_branch" : "master",
         "date" : "2023-03-02",
         "insecure_repo" : "",
         "dist" : "DateTime-Format-Genealogy",
         "repo_owner" : "nigelhorne",
         "repo" : "https://github.com/nigelhorne/DateTime-Format-Genealogy",
         "bugtracker" : "https://github.com/nigelhorne/DateTime-Format-Genealogy/issues"
      },
      {
         "dist" : "DateTime-Format-Text",
         "repo" : "https://github.com/nigelhorne/DateTime-Format-Text",
         "bugtracker" : "https://rt.cpan.org/Public/Dist/Display.html?Name=DateTime-Format-Text",
         "repo_owner" : "nigelhorne",
         "uses_rt" : "1",
         "name" : "DateTime-Format-Text-0.03",
         "repo_name" : "DateTime-Format-Text",
         "date" : "2023-04-29",
         "insecure_repo" : "",
         "repo_def_branch" : "master"
      },
      {
         "repo" : "https://github.com/nigelhorne/FCGI-Buffer",
         "bugtracker" : "https://github.com/nigelhorne/FCGI-Buffer/issues",
         "repo_owner" : "nigelhorne",
         "dist" : "FCGI-Buffer",
         "date" : "2023-02-26",
         "insecure_repo" : "",
         "repo_def_branch" : "master",
         "uses_rt" : "",
         "name" : "FCGI-Buffer-0.18",
         "repo_name" : "FCGI-Buffer"
      },
      {
         "dist" : "File-Open-NoCache-ReadOnly",
         "repo_owner" : "nigelhorne",
         "bugtracker" : "https://github.com/nigelhorne/File-Open-NoCache-ReadOnly/issues",
         "repo" : "https://github.com/nigelhorne/File-Open-NoCache-ReadOnly",
         "repo_name" : "File-Open-NoCache-ReadOnly",
         "uses_rt" : "",
         "name" : "File-Open-NoCache-ReadOnly-0.02",
         "repo_def_branch" : "master",
         "insecure_repo" : "",
         "date" : "2019-08-12"
      },
      {
         "name" : "File-Print-Many-0.02",
         "uses_rt" : "1",
         "repo_name" : "File-Print-Many",
         "insecure_repo" : "",
         "date" : "2022-06-20",
         "repo_def_branch" : "master",
         "dist" : "File-Print-Many",
         "bugtracker" : "https://rt.cpan.org/Public/Dist/Display.html?Name=File-Print-Many",
         "repo" : "https://github.com/nigelhorne/File-Print-Many",
         "repo_owner" : "nigelhorne"
      },
      {
         "dist" : "File-pfopen",
         "repo" : "https://github.com/nigelhorne/File-pfopen",
         "bugtracker" : "https://rt.cpan.org/Public/Dist/Display.html?Name=File-pfopen",
         "repo_owner" : "nigelhorne",
         "uses_rt" : "1",
         "name" : "File-pfopen-0.02",
         "repo_name" : "File-pfopen",
         "insecure_repo" : "",
         "date" : "2017-06-16",
         "repo_def_branch" : "master"
      },
      {
         "repo_owner" : "nigelhorne",
         "repo" : "https://github.com/nigelhorne/Genealogy-ChroniclingAmerica",
         "dist" : "Genealogy-ChroniclingAmerica",
         "repo_def_branch" : "master",
         "date" : "2019-11-17",
         "insecure_repo" : "",
         "repo_name" : "Genealogy-ChroniclingAmerica",
         "name" : "Genealogy-ChroniclingAmerica-0.03"
      },
      {
         "insecure_repo" : "",
         "date" : "2023-02-24",
         "repo_def_branch" : "master",
         "uses_rt" : "",
         "name" : "Genealogy-ObituaryDailyTimes-0.08",
         "repo_name" : "Genealogy-ObituaryDailyTimes",
         "bugtracker" : "https://github.com/nigelhorne/Genealogy-ObituaryDailyTimes/issues",
         "repo" : "https://github.com/nigelhorne/Genealogy-ObituaryDailyTimes",
         "repo_owner" : "nigelhorne",
         "dist" : "Genealogy-ObituaryDailyTimes"
      },
      {
         "dist" : "Genealogy-Wills",
         "bugtracker" : "https://github.com/nigelhorne/Genealogy-Wills/issues",
         "repo" : "https://github.com/nigelhorne/Genealogy-Wills",
         "repo_owner" : "nigelhorne",
         "name" : "Genealogy-Wills-0.02",
         "uses_rt" : "",
         "repo_name" : "Genealogy-Wills",
         "insecure_repo" : "",
         "date" : "2023-03-04",
         "repo_def_branch" : "master"
      },
      {
         "dist" : "Geo-Coder-Abbreviations",
         "bugtracker" : "https://github.com/nigelhorne/Geo-Coder-Abbreviations/issues",
         "repo" : "https://github.com/nigelhorne/Geo-Coder-Abbreviations",
         "repo_owner" : "nigelhorne",
         "name" : "Geo-Coder-Abbreviations-0.05",
         "uses_rt" : "",
         "repo_name" : "Geo-Coder-Abbreviations",
         "date" : "2022-07-22",
         "insecure_repo" : "",
         "repo_def_branch" : "master"
      },
      {
         "dist" : "Geo-Coder-CA",
         "repo_owner" : "nigelhorne",
         "bugtracker" : "https://github.com/nigelhorne/Geo-Coder-CA/issues",
         "repo" : "https://github.com/nigelhorne/Geo-Coder-CA",
         "repo_name" : "Geo-Coder-CA",
         "name" : "Geo-Coder-CA-0.14",
         "uses_rt" : "",
         "repo_def_branch" : "master",
         "insecure_repo" : "",
         "date" : "2023-04-21"
      },
      {
         "repo_def_branch" : "master",
         "date" : "2019-02-02",
         "insecure_repo" : "",
         "repo_name" : "Geo-Coder-DataScienceToolkit",
         "name" : "Geo-Coder-DataScienceToolkit-0.02",
         "uses_rt" : "1",
         "repo_owner" : "nigelhorne",
         "repo" : "https://github.com/nigelhorne/Geo-Coder-DataScienceToolkit",
         "bugtracker" : "https://rt.cpan.org/Public/Dist/Display.html?Name=Geo-Coder-DataScienceToolkit",
         "dist" : "Geo-Coder-DataScienceToolkit"
      },
      {
         "repo_owner" : "nigelhorne",
         "bugtracker" : "https://github.com/nigelhorne/Geo-Coder-Free/issues",
         "repo" : "https://github.com/nigelhorne/Geo-Coder-Free",
         "dist" : "Geo-Coder-Free",
         "repo_def_branch" : "master",
         "date" : "2023-03-24",
         "insecure_repo" : "",
         "repo_name" : "Geo-Coder-Free",
         "name" : "Geo-Coder-Free-0.31",
         "uses_rt" : ""
      },
      {
         "dist" : "Geo-Coder-GooglePlaces",
         "repo_owner" : "nigelhorne",
         "repo" : "https://github.com/nigelhorne/Geo-Coder-GooglePlaces",
         "bugtracker" : "https://github.com/nigelhorne/Geo-Coder-GooglePlaces/issues",
         "repo_name" : "Geo-Coder-GooglePlaces",
         "uses_rt" : "",
         "name" : "Geo-Coder-GooglePlaces-0.06",
         "repo_def_branch" : "master",
         "insecure_repo" : "",
         "date" : "2023-04-29"
      },
      {
         "repo_name" : "Geo-Coder-List",
         "name" : "Geo-Coder-List-0.29",
         "uses_rt" : "1",
         "repo_def_branch" : "master",
         "insecure_repo" : "",
         "date" : "2022-01-23",
         "dist" : "Geo-Coder-List",
         "repo_owner" : "nigelhorne",
         "repo" : "https://github.com/nigelhorne/Geo-Coder-List",
         "bugtracker" : "https://rt.cpan.org/Public/Dist/Display.html?Name=Geo-Coder-List"
      },
      {
         "repo_owner" : "nigelhorne",
         "repo" : "https://github.com/nigelhorne/Geo-Coder-Mapbox",
         "bugtracker" : "https://rt.cpan.org/Public/Dist/Display.html?Name=Geo-Coder-Mapbox",
         "dist" : "Geo-Coder-Mapbox",
         "repo_def_branch" : "master",
         "date" : "2021-10-05",
         "insecure_repo" : "",
         "repo_name" : "Geo-Coder-Mapbox",
         "uses_rt" : "1",
         "name" : "Geo-Coder-Mapbox-0.01"
      },
      {
         "dist" : "Geo-Coder-Postcodes",
         "repo" : "https://github.com/nigelhorne/Geo-Coder-Postcodes",
         "bugtracker" : "https://github.com/nigelhorne/Geo-Coder-Postcodes/issues",
         "repo_owner" : "nigelhorne",
         "name" : "Geo-Coder-Postcodes-0.07",
         "uses_rt" : "",
         "repo_name" : "Geo-Coder-Postcodes",
         "insecure_repo" : "",
         "date" : "2022-02-09",
         "repo_def_branch" : "master"
      },
      {
         "date" : "2023-01-31",
         "insecure_repo" : "",
         "repo_def_branch" : "master",
         "name" : "Geo-Coder-US-Census-0.06",
         "uses_rt" : "1",
         "repo_name" : "Geo-Coder-US-Census",
         "repo" : "https://github.com/nigelhorne/Geo-Coder-US-Census",
         "bugtracker" : "https://rt.cpan.org/Public/Dist/Display.html?Name=Geo-Coder-US-Census",
         "repo_owner" : "nigelhorne",
         "dist" : "Geo-Coder-US-Census"
      },
      {
         "repo_def_branch" : "master",
         "insecure_repo" : "",
         "date" : "2018-06-21",
         "repo_name" : "Geo-Coder-XYZ",
         "name" : "Geo-Coder-XYZ-0.09",
         "uses_rt" : "1",
         "repo_owner" : "nigelhorne",
         "bugtracker" : "https://rt.cpan.org/Public/Dist/Display.html?Name=Geo-Coder-XYZ",
         "repo" : "https://github.com/nigelhorne/Geo-Coder-XYZ",
         "dist" : "Geo-Coder-XYZ"
      },
      {
         "repo_owner" : "nigelhorne",
         "bugtracker" : "https://github.com/nigelhorne/Geo-GeoNames/issues",
         "repo" : "https://github.com/nigelhorne/Geo-GeoNames",
         "dist" : "Geo-GeoNames",
         "repo_def_branch" : "master",
         "date" : "2022-06-10",
         "insecure_repo" : "",
         "repo_name" : "Geo-GeoNames",
         "uses_rt" : "",
         "name" : "Geo-GeoNames-1.14"
      },
      {
         "repo_name" : "Geo-Location-Point",
         "name" : "Geo-Location-Point-0.08",
         "uses_rt" : "",
         "repo_def_branch" : "master",
         "insecure_repo" : "",
         "date" : "2023-03-17",
         "dist" : "Geo-Location-Point",
         "repo_owner" : "nigelhorne",
         "bugtracker" : "https://github.com/nigelhorne/Geo-Location-Point/issues",
         "repo" : "https://github.com/nigelhorne/Geo-Location-Point"
      },
      {
         "dist" : "HTML-SimpleLinkExtor",
         "repo" : "https://github.com/nigelhorne/HTML-SimpleLinkExtor",
         "bugtracker" : "https://github.com/nigelhorne/HTML-SimpleLinkExtor/issues",
         "repo_owner" : "nigelhorne",
         "uses_rt" : "",
         "name" : "HTML-SimpleLinkExtor-1.273",
         "repo_name" : "HTML-SimpleLinkExtor",
         "insecure_repo" : "",
         "date" : "2020-11-13",
         "repo_def_branch" : "master"
      },
      {
         "repo_owner" : "nigelhorne",
         "repo" : "https://github.com/nigelhorne/HTML-SocialMedia",
         "dist" : "HTML-SocialMedia",
         "repo_def_branch" : "master",
         "date" : "2020-01-18",
         "insecure_repo" : "",
         "repo_name" : "HTML-SocialMedia",
         "name" : "HTML-SocialMedia-0.28"
      },
      {
         "dist" : "LWP-UserAgent-Throttled",
         "repo_owner" : "nigelhorne",
         "bugtracker" : "https://github.com/nigelhorne/LWP-UserAgent-Throttled/issues",
         "repo" : "https://github.com/nigelhorne/LWP-UserAgent::Throttled",
         "repo_name" : "LWP-UserAgent::Throttled",
         "uses_rt" : "",
         "name" : "LWP-UserAgent-Throttled-0.09",
         "repo_def_branch" : "",
         "insecure_repo" : "",
         "date" : "2022-01-28"
      },
      {
         "insecure_repo" : "",
         "date" : "2021-08-02",
         "repo_def_branch" : "master",
         "name" : "Lingua-Conjunction-2.5",
         "uses_rt" : "1",
         "repo_name" : "Lingua-Conjunction",
         "repo" : "https://github.com/nigelhorne/Lingua-Conjunction",
         "bugtracker" : "https://rt.cpan.org/Public/Dist/Display.html?Name=Lingua-Conjunction",
         "repo_owner" : "nigelhorne",
         "dist" : "Lingua-Conjunction"
      },
      {
         "dist" : "Lingua-FR-Nums2Words",
         "repo" : "https://github.com/nigelhorne/Lingua-FR-Nums2Words",
         "bugtracker" : "https://github.com/nigelhorne/Lingua-FR-Nums2Words/issues",
         "repo_owner" : "nigelhorne",
         "name" : "Lingua-FR-Nums2Words-1.01",
         "uses_rt" : "",
         "repo_name" : "Lingua-FR-Nums2Words",
         "insecure_repo" : "",
         "date" : "2020-11-13",
         "repo_def_branch" : "main"
      },
      {
         "date" : "2022-03-15",
         "insecure_repo" : "",
         "repo_def_branch" : "master",
         "uses_rt" : "",
         "name" : "Lingua-String-0.03",
         "repo_name" : "Lingua-String",
         "repo" : "https://github.com/nigelhorne/Lingua-String",
         "bugtracker" : "https://github.com/nigelhorne/Lingua-String/issues",
         "repo_owner" : "nigelhorne",
         "dist" : "Lingua-String"
      },
      {
         "repo_name" : "Locale-AU-Info",
         "name" : "Locale-AU-0.01",
         "repo_def_branch" : "",
         "date" : "2020-05-18",
         "insecure_repo" : "",
         "dist" : "Locale-AU",
         "repo_owner" : "nigelhorne",
         "repo" : "https://github.com/nigelhorne/Locale-AU-Info"
      },
      {
         "repo_owner" : "nigelhorne",
         "repo" : "https://github.com/nigelhorne/Locale-CA-Info",
         "bugtracker" : "https://github.com/nigelhorne/Locale-CA/issues",
         "dist" : "Locale-CA",
         "repo_def_branch" : "",
         "date" : "2023-02-25",
         "insecure_repo" : "",
         "repo_name" : "Locale-CA-Info",
         "name" : "Locale-CA-0.05",
         "uses_rt" : ""
      },
      {
         "repo_name" : "Locale-Codes/Country-FR",
         "name" : "Locale-Codes-Country-FR-0.01",
         "uses_rt" : "",
         "repo_def_branch" : "",
         "insecure_repo" : "",
         "date" : "2019-09-13",
         "dist" : "Locale-Codes-Country-FR",
         "repo_owner" : "nigelhorne",
         "repo" : "https://github.com/nigelhorne/Locale-Codes/Country-FR",
         "bugtracker" : "https://github.com/nigelhorne/Locale-Codes/Country-FR/issues"
      },
      {
         "repo_owner" : "nigelhorne",
         "repo" : "https://github.com/nigelhorne/Locale-Places",
         "bugtracker" : "https://github.com/nigelhorne/Locale-Places/issues",
         "dist" : "Locale-Places",
         "repo_def_branch" : "master",
         "insecure_repo" : "",
         "date" : "2022-03-19",
         "repo_name" : "Locale-Places",
         "uses_rt" : "",
         "name" : "Locale-Places-0.07"
      },
      {
         "name" : "Log-Dispatch-Email-Sendmail-0.03",
         "uses_rt" : "",
         "repo_name" : "Log-Dispatch-Email-Sendmail",
         "insecure_repo" : "",
         "date" : "2022-01-06",
         "repo_def_branch" : "master",
         "dist" : "Log-Dispatch-Email-Sendmail",
         "repo" : "https://github.com/nigelhorne/Log-Dispatch-Email-Sendmail",
         "bugtracker" : "https://github.com/nigelhorne/Log-Dispatch-Email-Sendmail/issues",
         "repo_owner" : "nigelhorne"
      },
      {
         "dist" : "Log-Log4perl-Layout-Syslog",
         "repo_owner" : "nigelhorne",
         "repo" : "https://github.com/nigelhorne/Log-Log4perl-Layout-Syslog",
         "bugtracker" : "https://rt.cpan.org/Public/Dist/Display.html?Name=Log-Log4perl-Layout-Syslog",
         "repo_name" : "Log-Log4perl-Layout-Syslog",
         "name" : "Log-Log4perl-Layout-Syslog-0.02",
         "uses_rt" : "1",
         "repo_def_branch" : "master",
         "insecure_repo" : "",
         "date" : "2017-08-18"
      },
      {
         "repo" : "https://github.com/nigelhorne/Log::WarnDie",
         "bugtracker" : "https://rt.cpan.org/Public/Dist/Display.html?Name=Log::WarnDie",
         "repo_owner" : "nigelhorne",
         "dist" : "Log-WarnDie",
         "date" : "2017-09-12",
         "insecure_repo" : "",
         "repo_def_branch" : "",
         "uses_rt" : "1",
         "name" : "Log-WarnDie-0.09",
         "repo_name" : "Log::WarnDie"
      },
      {
         "name" : "Sub-Private-0.02",
         "repo_name" : "sub-private-perl/tree/master",
         "insecure_repo" : "1",
         "date" : "2020-09-17",
         "repo_def_branch" : "",
         "dist" : "Sub-Private",
         "repo" : "http://github.com/nigelhorne/sub-private-perl/tree/master",
         "repo_owner" : "nigelhorne"
      },
      {
         "repo" : "https://github.com/nigelhorne/Test-HTTPStatus",
         "bugtracker" : "https://github.com/nigelhorne/Test-HTTPStatus/issues",
         "repo_owner" : "nigelhorne",
         "dist" : "Test-HTTPStatus",
         "insecure_repo" : "",
         "date" : "2020-11-14",
         "repo_def_branch" : "master",
         "name" : "Test-HTTPStatus-2.05",
         "uses_rt" : "",
         "repo_name" : "Test-HTTPStatus"
      },
      {
         "repo_name" : "Text-Names-GB",
         "name" : "Text-Names-GB-0.03",
         "repo_def_branch" : "master",
         "insecure_repo" : "",
         "date" : "2019-04-21",
         "dist" : "Text-Names-GB",
         "repo_owner" : "nigelhorne",
         "repo" : "https://github.com/nigelhorne/Text-Names-GB"
      },
      {
         "insecure_repo" : "",
         "date" : "2023-04-07",
         "repo_def_branch" : "master",
         "name" : "TimeZone-TimeZoneDB-0.01",
         "uses_rt" : "",
         "repo_name" : "TimeZone-TimeZoneDB",
         "repo" : "https://github.com/nigelhorne/TimeZone-TimeZoneDB",
         "bugtracker" : "https://github.com/nigelhorne/TimeZone-TimeZoneDB/issues",
         "repo_owner" : "nigelhorne",
         "dist" : "TimeZone-TimeZoneDB"
      },
      {
         "dist" : "WWW-Scrape-FindaGrave",
         "repo_owner" : "nigelhorne",
         "repo" : "https://github.com/nigelhorne/WWW-Scrape-FindaGrave",
         "repo_name" : "WWW-Scrape-FindaGrave",
         "name" : "WWW-Scrape-FindaGrave-0.06",
         "repo_def_branch" : "master",
         "date" : "2018-08-28",
         "insecure_repo" : ""
      },
      {
         "bugtracker" : "https://github.com/nigelhorne/Weather-Meto/issues",
         "repo" : "https://github.com/nigelhorne/Weather-Meto",
         "repo_owner" : "nigelhorne",
         "dist" : "Weather-Meteo",
         "insecure_repo" : "",
         "date" : "2023-04-14",
         "repo_def_branch" : "",
         "uses_rt" : "",
         "name" : "Weather-Meteo-0.05",
         "repo_name" : "Weather-Meto"
      }
   ],
   "sort" : {
      "direction" : "asc",
      "column" : "0"
   }
}
