{
   "sort" : {
      "column" : "0",
      "direction" : "asc"
   },
   "ci" : {
      "use_cirrus" : 0,
      "use_travis" : 0,
      "use_travis_com" : 0,
      "use_codecov" : 0,
      "use_appveyor" : 0,
      "use_gh_actions" : 1,
      "use_kritika" : 0,
      "use_coveralls" : 1,
      "gh_workflow_names" : [
         "CI"
      ]
   },
   "author" : {
      "cpan" : "DAVECROSS",
      "github" : "davorg",
      "gravatar" : "https://secure.gravatar.com/avatar/d9f8bf9efe6afedec1b5b4ea24301933?s=130&d=identicon",
      "name" : "Dave Cross"
   },
   "modules" : [
      {
         "date" : "2020-12-06",
         "name" : "App-Aphra-0.0.6",
         "repo_name" : "app-aphra",
         "uses_rt" : "",
         "dist" : "App-Aphra",
         "insecure_repo" : "",
         "repo_owner" : "davorg",
         "repo" : "https://github.com/davorg/app-aphra",
         "repo_def_branch" : "master",
         "bugtracker" : "https://github.com/davorg/app-aphra/issues"
      },
      {
         "date" : "2021-05-13",
         "repo_name" : "app-cpanmodulesite",
         "name" : "App-CPANModuleSite-0.0.9",
         "insecure_repo" : "",
         "dist" : "App-CPANModuleSite",
         "uses_rt" : "",
         "repo" : "https://github.com/davorg/app-cpanmodulesite",
         "repo_def_branch" : "main",
         "repo_owner" : "davorg",
         "bugtracker" : "https://github.com/davorg/app-cpanmodulesite/issues"
      },
      {
         "uses_rt" : "",
         "dist" : "Array-Compare",
         "insecure_repo" : "",
         "date" : "2020-12-21",
         "name" : "Array-Compare-v3.0.8",
         "repo_name" : "array-compare",
         "repo_owner" : "davorg",
         "repo_def_branch" : "master",
         "repo" : "https://github.com/davorg/array-compare",
         "bugtracker" : "https://github.com/davorg/array-compare/issues"
      },
      {
         "dist" : "AudioFile-Info-MP3-ID3Lib",
         "uses_rt" : "",
         "insecure_repo" : "",
         "date" : "2021-03-02",
         "name" : "AudioFile-Info-MP3-ID3Lib-v1.8.1",
         "repo_name" : "audiofile-info-mp3-id3lib",
         "repo_owner" : "davorg",
         "repo" : "https://github.com/davorg/audiofile-info-mp3-id3lib",
         "repo_def_branch" : "master",
         "bugtracker" : "https://github.com/davorg/audiofile-info-mp3-id3lib/issues"
      },
      {
         "bugtracker" : "https://github.com/davorg/audiofile-info-mp3-tag/issues",
         "repo_owner" : "davorg",
         "repo_def_branch" : "master",
         "repo" : "https://github.com/davorg/audiofile-info-mp3-tag",
         "uses_rt" : "",
         "dist" : "AudioFile-Info-MP3-Tag",
         "insecure_repo" : "",
         "name" : "AudioFile-Info-MP3-Tag-v1.6.3",
         "repo_name" : "audiofile-info-mp3-tag",
         "date" : "2021-01-04"
      },
      {
         "insecure_repo" : "",
         "dist" : "AudioFile-Info-Ogg-Vorbis-Header-PurePerl",
         "uses_rt" : "",
         "date" : "2021-01-23",
         "repo_name" : "audiofile-info-ogg-vorbis-header-pureperl",
         "name" : "AudioFile-Info-Ogg-Vorbis-Header-PurePerl-v1.5.5",
         "repo" : "https://github.com/davorg/audiofile-info-ogg-vorbis-header-pureperl",
         "repo_def_branch" : "master",
         "repo_owner" : "davorg",
         "bugtracker" : "https://github.com/davorg/audiofile-info-ogg-vorbis-header-pureperl/issues"
      },
      {
         "repo_name" : "audiofile-info-ogg-vorbis-header",
         "name" : "AudioFile-Info-Ogg-Vorbis-Header-v1.8.3",
         "date" : "2021-01-04",
         "insecure_repo" : "",
         "uses_rt" : "",
         "dist" : "AudioFile-Info-Ogg-Vorbis-Header",
         "bugtracker" : "https://github.com/davorg/audiofile-info-ogg-vorbis-header/issues",
         "repo" : "https://github.com/davorg/audiofile-info-ogg-vorbis-header",
         "repo_def_branch" : "master",
         "repo_owner" : "davorg"
      },
      {
         "repo_name" : "audiofile-info",
         "name" : "AudioFile-Info-v2.0.2",
         "date" : "2021-01-04",
         "insecure_repo" : "",
         "dist" : "AudioFile-Info",
         "uses_rt" : "",
         "bugtracker" : "https://github.com/davorg/audiofile-info/issues",
         "repo_def_branch" : "master",
         "repo" : "https://github.com/davorg/audiofile-info",
         "repo_owner" : "davorg"
      },
      {
         "repo_owner" : "davorg",
         "repo_def_branch" : "master",
         "repo" : "git://github.com/davorg/Feed-Find.git",
         "dist" : "Feed-Find",
         "insecure_repo" : "",
         "date" : "2022-10-18",
         "name" : "Feed-Find-0.13",
         "repo_name" : "Feed-Find"
      },
      {
         "date" : "2021-01-22",
         "repo_name" : "genealogy-ahnentafel",
         "name" : "Genealogy-Ahnentafel-1.0.3",
         "insecure_repo" : "",
         "uses_rt" : "",
         "dist" : "Genealogy-Ahnentafel",
         "repo_def_branch" : "master",
         "repo" : "https://github.com/davorg/genealogy-ahnentafel",
         "repo_owner" : "davorg",
         "bugtracker" : "https://github.com/davorg/genealogy-ahnentafel/issues"
      },
      {
         "name" : "Genealogy-AncestorChart-0.0.2",
         "repo_name" : "genealogy-ancestorchart",
         "date" : "2022-02-15",
         "dist" : "Genealogy-AncestorChart",
         "uses_rt" : "",
         "insecure_repo" : "",
         "bugtracker" : "https://github.com/davorg/genealogy-ancestorchart/issues",
         "repo_owner" : "davorg",
         "repo_def_branch" : "main",
         "repo" : "https://github.com/davorg/genealogy-ancestorchart"
      },
      {
         "insecure_repo" : "",
         "uses_rt" : "",
         "dist" : "Genealogy-Relationship",
         "date" : "2021-01-12",
         "repo_name" : "genealogy-relationship",
         "name" : "Genealogy-Relationship-0.0.5",
         "repo_def_branch" : "master",
         "repo" : "https://github.com/davorg/genealogy-relationship",
         "repo_owner" : "davorg",
         "bugtracker" : "https://github.com/davorg/genealogy-relationship/issues"
      },
      {
         "name" : "MooX-Role-JSON_LD-1.0.1",
         "repo_name" : "moox-role-json_ld",
         "date" : "2021-06-06",
         "uses_rt" : "",
         "dist" : "MooX-Role-JSON_LD",
         "insecure_repo" : "",
         "bugtracker" : "https://github.com/davorg/moox-role-json_ld/issues",
         "repo_owner" : "davorg",
         "repo_def_branch" : "master",
         "repo" : "https://github.com/davorg/moox-role-json_ld"
      },
      {
         "bugtracker" : "https://github.com/p5-number-fraction/number-fraction/issues",
         "repo_def_branch" : "master",
         "repo" : "https://github.com/p5-number-fraction/number-fraction",
         "repo_owner" : "p5-number-fraction",
         "repo_name" : "number-fraction",
         "name" : "Number-Fraction-v3.0.4",
         "date" : "2021-04-15",
         "insecure_repo" : "",
         "uses_rt" : "",
         "dist" : "Number-Fraction"
      },
      {
         "dist" : "Ogg-Vorbis-Header",
         "uses_rt" : "",
         "insecure_repo" : "",
         "date" : "2021-01-04",
         "name" : "Ogg-Vorbis-Header-0.11",
         "repo_name" : "Ogg-Vorbis-Header",
         "repo_owner" : "davorg",
         "repo" : "https://github.com/davorg/Ogg-Vorbis-Header",
         "repo_def_branch" : "master",
         "bugtracker" : "https://github.com/davorg/Ogg-Vorbis-Header/issues"
      },
      {
         "dist" : "Ogg-Vorbis-Header-PurePerl",
         "uses_rt" : "",
         "insecure_repo" : "",
         "name" : "Ogg-Vorbis-Header-PurePerl-1.05",
         "repo_name" : "perl-ogg-vorbis-header-pureperl",
         "date" : "2020-12-06",
         "bugtracker" : "https://github.com/davorg/perl-ogg-vorbis-header-pureperl/issues",
         "repo_owner" : "davorg",
         "repo" : "https://github.com/davorg/perl-ogg-vorbis-header-pureperl",
         "repo_def_branch" : "master"
      },
      {
         "bugtracker" : "https://github.com/davorg/parse-rpm-spec/issues",
         "repo_def_branch" : "master",
         "repo" : "https://github.com/davorg/parse-rpm-spec",
         "repo_owner" : "davorg",
         "repo_name" : "parse-rpm-spec",
         "name" : "Parse-RPM-Spec-v1.1.2",
         "date" : "2023-01-13",
         "insecure_repo" : "",
         "uses_rt" : "",
         "dist" : "Parse-RPM-Spec"
      },
      {
         "bugtracker" : "https://github.com/davorg/perlanet/issues",
         "repo_owner" : "davorg",
         "repo_def_branch" : "master",
         "repo" : "https://github.com/davorg/perlanet",
         "uses_rt" : "",
         "dist" : "Perlanet",
         "insecure_repo" : "",
         "name" : "Perlanet-v3.0.0",
         "repo_name" : "perlanet",
         "date" : "2023-03-01"
      },
      {
         "insecure_repo" : "",
         "dist" : "Plack-App-DirectoryIndex",
         "uses_rt" : "",
         "date" : "2020-12-21",
         "repo_name" : "plack-app-directoryindex",
         "name" : "Plack-App-DirectoryIndex-0.0.3",
         "repo_def_branch" : "main",
         "repo" : "https://github.com/davorg/plack-app-directoryindex",
         "repo_owner" : "davorg",
         "bugtracker" : "https://github.com/davorg/plack-app-directoryindex/issues"
      },
      {
         "bugtracker" : "https://github.com/ranguard/plack-middleware-dirindex/issues",
         "repo" : "https://github.com/ranguard/plack-middleware-dirindex",
         "repo_def_branch" : "master",
         "repo_owner" : "ranguard",
         "repo_name" : "plack-middleware-dirindex",
         "name" : "Plack-Middleware-DirIndex-1.01",
         "date" : "2022-03-26",
         "insecure_repo" : "",
         "uses_rt" : "",
         "dist" : "Plack-Middleware-DirIndex"
      },
      {
         "bugtracker" : "https://github.com/davorg/qmail-queuehandler/issues",
         "repo_owner" : "davorg",
         "repo" : "https://github.com/davorg/qmail-queuehandler",
         "repo_def_branch" : "master",
         "name" : "QMail-QueueHandler-2.0.4",
         "repo_name" : "qmail-queuehandler",
         "date" : "2021-01-13",
         "dist" : "QMail-QueueHandler",
         "uses_rt" : "",
         "insecure_repo" : ""
      },
      {
         "date" : "2021-01-12",
         "repo_name" : "svg-christmastree",
         "name" : "SVG-ChristmasTree-0.0.5",
         "insecure_repo" : "",
         "dist" : "SVG-ChristmasTree",
         "uses_rt" : "",
         "repo" : "https://github.com/davorg/svg-christmastree",
         "repo_def_branch" : "master",
         "repo_owner" : "davorg",
         "bugtracker" : "https://github.com/davorg/svg-christmastree/issues"
      },
      {
         "repo_def_branch" : "master",
         "repo" : "https://github.com/davorg/svg-timeline",
         "repo_owner" : "davorg",
         "bugtracker" : "https://github.com/davorg/svg-timeline/issues",
         "insecure_repo" : "",
         "uses_rt" : "",
         "dist" : "SVG-Timeline",
         "date" : "2022-11-01",
         "repo_name" : "svg-timeline",
         "name" : "SVG-Timeline-0.1.3"
      },
      {
         "repo_owner" : "davorg",
         "repo_def_branch" : "master",
         "repo" : "https://github.com/davorg/svg-timeline-genealogy",
         "bugtracker" : "https://github.com/davorg/svg-timeline-genealogy/issues",
         "uses_rt" : "",
         "dist" : "SVG-Timeline-Genealogy",
         "insecure_repo" : "",
         "date" : "2021-03-22",
         "name" : "SVG-Timeline-Genealogy-0.0.5",
         "repo_name" : "svg-timeline-genealogy"
      },
      {
         "name" : "SVG-TrafficLight-0.1.4",
         "repo_name" : "svg-trafficlight",
         "date" : "2020-12-22",
         "dist" : "SVG-TrafficLight",
         "uses_rt" : "",
         "insecure_repo" : "",
         "bugtracker" : "https://github.com/davorg/svg-trafficlight/issues",
         "repo_owner" : "davorg",
         "repo_def_branch" : "master",
         "repo" : "https://github.com/davorg/svg-trafficlight"
      },
      {
         "date" : "2021-01-13",
         "repo_name" : "symbol-approx-sub",
         "name" : "Symbol-Approx-Sub-v3.1.3",
         "insecure_repo" : "",
         "uses_rt" : "",
         "dist" : "Symbol-Approx-Sub",
         "repo" : "https://github.com/davorg/symbol-approx-sub",
         "repo_def_branch" : "master",
         "repo_owner" : "davorg",
         "bugtracker" : "https://github.com/davorg/symbol-approx-sub/issues"
      },
      {
         "uses_rt" : "",
         "dist" : "Template-Plugin-AudioFile-Info",
         "insecure_repo" : "",
         "date" : "2021-01-23",
         "name" : "Template-Plugin-AudioFile-Info-v2.0.2",
         "repo_name" : "template-plugin-audiofile-info",
         "repo_owner" : "davorg",
         "repo_def_branch" : "master",
         "repo" : "https://github.com/davorg/template-plugin-audiofile-info",
         "bugtracker" : "https://github.com/davorg/template-plugin-audiofile-info/issues"
      },
      {
         "bugtracker" : "https://github.com/davorg/template-plugin-rpm2/issues",
         "repo_owner" : "davorg",
         "repo" : "https://github.com/davorg/template-plugin-rpm2",
         "repo_def_branch" : "master",
         "name" : "Template-Plugin-RPM2-v1.3.4",
         "repo_name" : "template-plugin-rpm2",
         "date" : "2021-01-25",
         "dist" : "Template-Plugin-RPM2",
         "uses_rt" : "",
         "insecure_repo" : ""
      },
      {
         "repo_name" : "template-plugin-xml-feed",
         "name" : "Template-Plugin-XML-Feed-v1.0.3",
         "date" : "2021-01-28",
         "insecure_repo" : "",
         "uses_rt" : "",
         "dist" : "Template-Plugin-XML-Feed",
         "bugtracker" : "https://github.com/davorg/template-plugin-xml-feed/issues",
         "repo_def_branch" : "master",
         "repo" : "https://github.com/davorg/template-plugin-xml-feed",
         "repo_owner" : "davorg"
      },
      {
         "name" : "Template-Provider-Pandoc-0.0.4",
         "repo_name" : "template-provider-pandoc",
         "date" : "2020-12-23",
         "dist" : "Template-Provider-Pandoc",
         "uses_rt" : "",
         "insecure_repo" : "",
         "bugtracker" : "https://github.com/davorg/template-provider-pandoc/issues",
         "repo_owner" : "davorg",
         "repo_def_branch" : "master",
         "repo" : "https://github.com/davorg/template-provider-pandoc"
      },
      {
         "bugtracker" : "https://github.com/davorg/tie-hash-cannabinol/issues",
         "repo_def_branch" : "master",
         "repo" : "https://github.com/davorg/tie-hash-cannabinol",
         "repo_owner" : "davorg",
         "insecure_repo" : "",
         "uses_rt" : "",
         "dist" : "Tie-Hash-Cannabinol",
         "repo_name" : "tie-hash-cannabinol",
         "name" : "Tie-Hash-Cannabinol-v1.12.2",
         "date" : "2021-01-25"
      },
      {
         "dist" : "Tie-Hash-FixedKeys",
         "uses_rt" : "",
         "insecure_repo" : "",
         "name" : "Tie-Hash-FixedKeys-v1.13.2",
         "repo_name" : "tie-hash-fixedkeys",
         "date" : "2021-01-25",
         "bugtracker" : "https://github.com/davorg/tie-hash-fixedkeys/issues",
         "repo_owner" : "davorg",
         "repo" : "https://github.com/davorg/tie-hash-fixedkeys",
         "repo_def_branch" : "master"
      },
      {
         "bugtracker" : "https://github.com/davorg/tie-hash-regex/issues",
         "repo" : "https://github.com/davorg/tie-hash-regex",
         "repo_def_branch" : "master",
         "repo_owner" : "davorg",
         "insecure_repo" : "",
         "dist" : "Tie-Hash-Regex",
         "uses_rt" : "",
         "repo_name" : "tie-hash-regex",
         "name" : "Tie-Hash-Regex-1.14",
         "date" : "2021-01-25"
      },
      {
         "repo_def_branch" : "master",
         "repo" : "https://github.com/davorg/xml-feed",
         "repo_owner" : "davorg",
         "bugtracker" : "https://github.com/davorg/xml-feed/issues",
         "insecure_repo" : "",
         "dist" : "XML-Feed",
         "uses_rt" : "",
         "date" : "2021-05-25",
         "repo_name" : "xml-feed",
         "name" : "XML-Feed-0.63"
      }
   ]
}
